main.py
akugatauiniapatapihelo-0.1.0.dist-info/METADATA
akugatauiniapatapihelo-0.1.0.dist-info/WHEEL
akugatauiniapatapihelo-0.1.0.dist-info/top_level.txt
akugatauiniapatapihelo-0.1.0.dist-info/RECORD
