Metadata-Version: 2.4
Name: akugatauiniapatapihelo
Version: 0.1.0
Summary: A simple hello world Python package.
Requires-Python: >=3.13
